eth_accounts_index/__init__.py
eth_accounts_index/registry.py
eth_accounts_index/data/AccountsIndex.bin
eth_accounts_index/data/AccountsIndex.json
eth_accounts_index/runnable/add.py
eth_accounts_index/runnable/deploy.py
eth_accounts_index-0.0.8.dist-info/LICENSE
eth_accounts_index-0.0.8.dist-info/METADATA
eth_accounts_index-0.0.8.dist-info/WHEEL
eth_accounts_index-0.0.8.dist-info/entry_points.txt
eth_accounts_index-0.0.8.dist-info/top_level.txt
eth_accounts_index-0.0.8.dist-info/RECORD
