Metadata-Version: 2.1
Name: eth-accounts-index
Version: 0.0.8
Summary: Accounts index evm contract tooling with permissioned writes
Home-page: https://gitlab.com/nolash/eth-accounts-index
Author: Louis Holbrook
Author-email: dev@holbrook.no
License: GPL3
Keywords: ethereum
Platform: UNKNOWN
Classifier: Programming Language :: Python :: 3
Classifier: Operating System :: OS Independent
Classifier: Development Status :: 3 - Alpha
Classifier: Environment :: No Input/Output (Daemon)
Classifier: Intended Audience :: Developers
Classifier: License :: OSI Approved :: GNU General Public License v3 or later (GPLv3+)
Classifier: Topic :: Internet
Requires-Python: >=3.6
Requires-Dist: confini (==0.3.5)
Requires-Dist: web3 (==5.12.2)
Provides-Extra: testing
Requires-Dist: pytest (==6.0.1) ; extra == 'testing'
Requires-Dist: eth-tester (==0.5.0b2) ; extra == 'testing'
Requires-Dist: py-evm (==0.3.0a20) ; extra == 'testing'
